distseal/__init__.py
distseal/main.py
distseal-0.0.1.dist-info/licenses/LICENSE
distseal-0.0.1.dist-info/WHEEL
distseal-0.0.1.dist-info/METADATA
distseal-0.0.1.dist-info/RECORD
