Metadata-Version: 2.4
Name: distseal
Version: 0.0.1
Summary: Posthoc Watermarking for LLM Generated Text
Author: Facebook AI Research
Requires-Python: >=3.10
Classifier: License :: OSI Approved :: MIT License
Classifier: Topic :: Scientific/Engineering
Classifier: Topic :: Scientific/Engineering :: Artificial Intelligence
Classifier: Development Status :: 4 - Beta
License-File: LICENSE
Requires-Dist: torch
Requires-Dist: soundfile ; extra == "audio"
Requires-Dist: numpy<2 ; extra == "audio"
Requires-Dist: pesq ; extra == "audio"
Requires-Dist: torchaudio ; extra == "audio"
Requires-Dist: julius ; extra == "audio"
Requires-Dist: pystoi ; extra == "audio"
Requires-Dist: flake8 ; extra == "dev"
Requires-Dist: mypy ; extra == "dev"
Requires-Dist: pytest ; extra == "dev"
Requires-Dist: black ; extra == "dev"
Requires-Dist: isort ; extra == "dev"
Requires-Dist: flake8 ; extra == "dev"
Requires-Dist: pre-commit ; extra == "dev"
Requires-Dist: torchvision ; extra == "image"
Requires-Dist: scikit-image ; extra == "image"
Requires-Dist: lpips ; extra == "image"
Requires-Dist: kornia ; extra == "image"
Requires-Dist: torchvision ; extra == "video"
Requires-Dist: scikit-image ; extra == "video"
Requires-Dist: lpips ; extra == "video"
Requires-Dist: kornia ; extra == "video"
Requires-Dist: av ; extra == "video"
Requires-Dist: ffmpeg-python ; extra == "video"
Project-URL: Source, https://github.com/facebookresearch/textseal
Project-URL: Tracker, https://github.com/facebookresearch/textseal/issues
Provides-Extra: audio
Provides-Extra: dev
Provides-Extra: image
Provides-Extra: video
